vnpy_esunny-1.0.2.2.7.dist-info/METADATA
vnpy_esunny-1.0.2.2.7.dist-info/WHEEL
vnpy_esunny/api/vnesunnymd.cp313-win_amd64.pyd
vnpy_esunny/api/vnesunnymd.cp313-win_amd64.lib
vnpy_esunny/api/vnesunnytd.cp313-win_amd64.pyd
vnpy_esunny/api/vnesunnytd.cp313-win_amd64.lib
vnpy_esunny/__init__.py
vnpy_esunny/api/__init__.py
vnpy_esunny/api/esunny_constant.py
vnpy_esunny/gateway/__init__.py
vnpy_esunny/gateway/esunny_gateway.py
vnpy_esunny/api/TapQuoteAPI.dll
vnpy_esunny/api/TapDataCollectAPI.dll
vnpy_esunny/api/EsTdAPI.dll
vnpy_esunny/api/ITapTdAPI.dll
vnpy_esunny/api/ITapSETdAPI.dll
vnpy_esunny/api/TapTdAPI.dll
vnpy_esunny-1.0.2.2.7.dist-info/RECORD
