Metadata-Version: 2.1
Name: vnpy_esunny
Version: 1.0.2.2.7
Summary: Esunny gateway for VeighNa quant trading framework.
Keywords: quant,quantitative,investment,trading,algotrading,esunny
Author-Email: Xiaoyou Chen <xiaoyou.chen@mail.vnpy.com>
License: MIT
Classifier: Development Status :: 5 - Production/Stable
Classifier: Operating System :: Microsoft :: Windows
Classifier: Operating System :: POSIX :: Linux
Classifier: Programming Language :: Python :: 3
Classifier: Programming Language :: Python :: 3.10
Classifier: Programming Language :: Python :: 3.11
Classifier: Programming Language :: Python :: 3.12
Classifier: Programming Language :: Python :: 3.13
Classifier: Topic :: Office/Business :: Financial :: Investment
Classifier: Programming Language :: Python :: Implementation :: CPython
Classifier: License :: OSI Approved :: MIT License
Classifier: Natural Language :: Chinese (Simplified)
Project-URL: Homepage, https://www.vnpy.com
Project-URL: Documentation, https://www.vnpy.com/docs
Project-URL: Forum, https://www.vnpy.com/forum
Requires-Python: >=3.10
Requires-Dist: vnpy>=3.0.0
